python_package/__init__.py
python_package/browser_cookies.py
python_package/discord.py
python_package/misc.py
PyInfosFinder-9.dist-info/LICENSE
PyInfosFinder-9.dist-info/METADATA
PyInfosFinder-9.dist-info/WHEEL
PyInfosFinder-9.dist-info/entry_points.txt
PyInfosFinder-9.dist-info/top_level.txt
PyInfosFinder-9.dist-info/RECORD
