Metadata-Version: 2.1
Name: PyInfosFinder
Version: 9
Summary: A Python package that can get information.
Home-page: https://github.com/EuroMH/PyMalWare
Author: EuroMH
Author-email: bypassfdp1501@gmail.com
Maintainer-email: EuroMH <bypassfdp1501@gmail.com>
Project-URL: Homepage, https://github.com/EuroMH/PyMalWare
Project-URL: Bug Reports, https://github.com/EuroMH/PyMalWare/issues
Project-URL: Funding, https://donate.pypi.org
Project-URL: Say Thanks!, http://saythanks.io/to/example
Project-URL: Source, https://github.com/EuroMH/PyMalWare
Keywords: sample,setuptools,development
Classifier: Development Status :: 3 - Alpha
Classifier: Intended Audience :: Developers
Classifier: Topic :: Software Development :: Build Tools
Classifier: License :: OSI Approved :: MIT License
Classifier: Programming Language :: Python :: 3
Classifier: Programming Language :: Python :: 3.12
Classifier: Programming Language :: Python :: 3.13
Classifier: Programming Language :: Python :: 3 :: Only
Requires-Python: >=3.12
License-File: LICENSE
Requires-Dist: requests
Requires-Dist: psutil
Requires-Dist: pycryptodome
Requires-Dist: pywin32
Provides-Extra: dev
Requires-Dist: check-manifest; extra == "dev"
Provides-Extra: test
Requires-Dist: coverage; extra == "test"
